pallma/__init__.py
pallma/cli/__init__.py
pallma/cli/docker-compose.yaml
pallma/cli/main.py
pallma/cli/services/display.py
pallma/cli/services/collector/otel-collector-to-kafka.yaml
pallma/cli/services/predictor/Dockerfile
pallma/cli/services/predictor/README.md
pallma/cli/services/predictor/pyproject.toml
pallma/cli/services/predictor/app/main.py
pallma/cli/services/predictor/app/model.py
pallma/cli/services/processor/Dockerfile
pallma/cli/services/processor/README.md
pallma/cli/services/processor/main.py
pallma/cli/services/processor/pyproject.toml
pallma/sdk/__init__.py
pallma_guard-0.0.3.dist-info/METADATA
pallma_guard-0.0.3.dist-info/WHEEL
pallma_guard-0.0.3.dist-info/entry_points.txt
pallma_guard-0.0.3.dist-info/licenses/LICENSE
pallma_guard-0.0.3.dist-info/RECORD
