Metadata-Version: 2.4
Name: pallma-guard
Version: 0.0.3
Summary: The Security Observability Layer for AI Agents
Author: Dionysis Varelas (@dvarelas), Pavlos Mitsoulis (@pm3310)
License: Apache License 2.0
License-File: LICENSE
Keywords: AI Agents,Cybersecurity,LLM
Classifier: Intended Audience :: Developers
Classifier: License :: OSI Approved :: Apache Software License
Classifier: Operating System :: MacOS
Classifier: Operating System :: POSIX :: Linux
Classifier: Topic :: Scientific/Engineering :: Artificial Intelligence
Requires-Python: >=3.12
Requires-Dist: typer>=0.16.0
Provides-Extra: sdk
Requires-Dist: traceloop-sdk>=0.43.1; extra == 'sdk'
